pywbem/__init__.py
pywbem/_cim_constants.py
pywbem/_cim_http.py
pywbem/_cim_obj.py
pywbem/_cim_operations.py
pywbem/_cim_types.py
pywbem/_cim_xml.py
pywbem/_cliutils.py
pywbem/_exceptions.py
pywbem/_features.py
pywbem/_listener.py
pywbem/_logging.py
pywbem/_mof_compiler.py
pywbem/_moflextab.py
pywbem/_mofparsetab.py
pywbem/_nocasedict.py
pywbem/_recorder.py
pywbem/_server.py
pywbem/_statistics.py
pywbem/_subscription_manager.py
pywbem/_tupleparse.py
pywbem/_tupletree.py
pywbem/_units.py
pywbem/_utils.py
pywbem/_valuemapping.py
pywbem/_version.py
pywbem/_version_scm.py
pywbem/_warnings.py
pywbem/config.py
pywbem/_vendor/__init__.py
pywbem/_vendor/nocasedict/LICENSE
pywbem/_vendor/nocasedict/__init__.py
pywbem/_vendor/nocasedict/_hashable.py
pywbem/_vendor/nocasedict/_keyableby.py
pywbem/_vendor/nocasedict/_nocasedict.py
pywbem/_vendor/nocasedict/_utils.py
pywbem/_vendor/nocasedict/_version.py
pywbem/_vendor/nocasedict/py.typed
pywbem/_vendor/nocaselist/LICENSE
pywbem/_vendor/nocaselist/__init__.py
pywbem/_vendor/nocaselist/_nocaselist.py
pywbem/_vendor/nocaselist/_version.py
pywbem/_vendor/nocaselist/py.typed
pywbem-1.9.0.data/scripts/mof_compiler
pywbem-1.9.0.data/scripts/mof_compiler.bat
pywbem_mock/__init__.py
pywbem_mock/_baseprovider.py
pywbem_mock/_baserepository.py
pywbem_mock/_dmtf_cim_schema.py
pywbem_mock/_inmemoryrepository.py
pywbem_mock/_instancewriteprovider.py
pywbem_mock/_mainprovider.py
pywbem_mock/_methodprovider.py
pywbem_mock/_mockmofwbemconnection.py
pywbem_mock/_namespaceprovider.py
pywbem_mock/_providerdependentregistry.py
pywbem_mock/_providerdispatcher.py
pywbem_mock/_providerregistry.py
pywbem_mock/_resolvermixin.py
pywbem_mock/_subscriptionproviders.py
pywbem_mock/_utils.py
pywbem_mock/_wbemconnection_mock.py
pywbem_mock/config.py
pywbem-1.9.0.dist-info/METADATA
pywbem-1.9.0.dist-info/WHEEL
pywbem-1.9.0.dist-info/top_level.txt
pywbem-1.9.0.dist-info/zip-safe
pywbem-1.9.0.dist-info/RECORD
