Metadata-Version: 2.4
Name: pywbem
Version: 1.9.0
Summary: pywbem - A WBEM client
Author-email: Tim Potter <tpot@hp.com>
Maintainer-email: Andreas Maier <maiera@de.ibm.com>, Karl Schopmeyer <k.schopmeyer@swbell.net>
License-Expression: LGPL-2.1-or-later
Project-URL: Homepage, https://pywbem.github.io/pywbem/
Project-URL: Bug Tracker, https://github.com/pywbem/pywbem/issues
Project-URL: Documentation, https://pywbem.readthedocs.io/en/latest/
Project-URL: Source Code, https://github.com/pywbem/pywbem
Project-URL: Changelog, https://pywbem.readthedocs.io/en/latest/changes.html
Keywords: cim,wbem,client
Platform: any
Classifier: Development Status :: 5 - Production/Stable
Classifier: Intended Audience :: Developers
Classifier: Intended Audience :: System Administrators
Classifier: Topic :: Software Development :: Libraries :: Python Modules
Classifier: Topic :: System :: Systems Administration
Classifier: Environment :: Console
Classifier: Operating System :: OS Independent
Classifier: Programming Language :: Python :: 3
Classifier: Programming Language :: Python :: 3.9
Classifier: Programming Language :: Python :: 3.10
Classifier: Programming Language :: Python :: 3.11
Classifier: Programming Language :: Python :: 3.12
Classifier: Programming Language :: Python :: 3.13
Classifier: Programming Language :: Python :: 3.14
Requires-Python: >=3.9
Requires-Dist: ply>=3.10
Requires-Dist: PyYAML>=6.0.2
Requires-Dist: requests>=2.32.4
Requires-Dist: yamlloader>=0.5.5
Requires-Dist: typing-extensions>=4.14.1
Requires-Dist: setuptools!=61.0.0
Requires-Dist: urllib3>=2.6.0
Requires-Dist: certifi>=2024.07.04
Requires-Dist: idna>=3.7
Provides-Extra: test
Requires-Dist: six>=1.14.0; python_version <= "3.9" and extra == "test"
Requires-Dist: six>=1.16.0; python_version >= "3.10" and extra == "test"
Requires-Dist: packaging>=24.2; extra == "test"
Requires-Dist: pytest>=8.0.2; extra == "test"
Requires-Dist: testfixtures>=6.9.0; extra == "test"
Requires-Dist: colorama>=0.4.5; extra == "test"
Requires-Dist: FormEncode>=2.1.1; extra == "test"
Requires-Dist: easy-vault>=0.7.0; extra == "test"
Requires-Dist: easy-server>=0.8.0; extra == "test"
Requires-Dist: pytest-easy-server>=0.8.0; extra == "test"
Requires-Dist: cryptography>=43.0.1; extra == "test"
Requires-Dist: keyring>=18.0.0; extra == "test"
Requires-Dist: jsonschema>=4.18.0; extra == "test"
Requires-Dist: requests-mock>=1.6.0; extra == "test"
Requires-Dist: requests-toolbelt>=0.8.0; extra == "test"
Requires-Dist: yagot>=0.5.0; extra == "test"
Requires-Dist: importlib-metadata>=4.8.3; extra == "test"
Requires-Dist: tzdata>=2024.1; sys_platform == "win32" and extra == "test"
Requires-Dist: pluggy>=1.3.0; extra == "test"
Requires-Dist: decorator>=4.0.11; extra == "test"
Requires-Dist: lxml>=6.0.2; extra == "test"
Requires-Dist: virtualenv>=20.26.6; extra == "test"
